test_password_maker/__init__.py
test_password_maker/password.py
test_password_maker-0.0.2.dist-info/METADATA
test_password_maker-0.0.2.dist-info/WHEEL
test_password_maker-0.0.2.dist-info/top_level.txt
test_password_maker-0.0.2.dist-info/RECORD
