Metadata-Version: 2.1
Name: test-password-maker
Version: 0.0.2
Summary: package build test
Home-page: https://github.com/nicecoding1/
Author: Sohee Han
Author-email: eng.sohee@gmail.com
License: UNKNOWN
Platform: UNKNOWN
Classifier: Programming Language :: Python :: 3
Classifier: License :: OSI Approved :: MIT License
Classifier: Operating System :: OS Independent
Requires-Python: >=3.6
